mux5in1.v
module mux5in1( data_a, data_b,  i_cntr, i_clk, i_reset, o_data);

input [7 : 0] data_a, data_b;
input  i_clk, i_reset;
input [2 :0] i_cntr;
output reg [7 : 0] o_data;

always@(posedge i_clk)begin
if (i_reset) begin
	o_data <= 0;
end else begin 
	case (i_cntr)
		3'b000: o_data <= data_a;
		3'b001: o_data <= data_b;
	default: o_data <= 0;	
	endcase
	end
end


endmodule

mux5in1_tb.v
`timescale 1ns / 1ps

module mux5in1_tb;

parameter NANOS = 1;



reg  i_clk, i_reset;
reg [7 : 0] data_a, data_b;
reg [2 : 0] i_cntr;
wire [7 : 0] o_data;



mux5in1 mux5in1 (.i_clk (i_clk), 
            .i_reset(i_reset),
            .i_cntr(i_cntr),
            .data_a(data_a),
            .data_b(data_b),
            .o_data(o_data));

            
initial begin
    data_a = 0;
    data_b = 0;
    i_cntr = 0;
    i_clk = 0;
    i_reset = 0;
end     

initial begin
    #(NANOS*3) i_reset = 1;
    #(NANOS*5) i_reset = 0;
end

initial begin
    repeat (14) #(NANOS*7) i_cntr = i_cntr + 1;
end
initial begin
    repeat (20) #(NANOS*5) data_a = data_a + 1;
end 
initial begin
    repeat (10) #(NANOS*10) data_b = data_b + 2;
    end
initial begin
    repeat (33) #(NANOS*3) i_clk = ~i_clk;
    $finish;
end
 
initial
 begin
    $dumpfile("mux5in1.vcd");
    $dumpvars(0,mux5in1_tb);
 end



  
endmodule

mux5in1.vcd
$date
	Thu Jan 19 17:00:59 2023
$end
$version
	Icarus Verilog
$end
$timescale
	1ps
$end
$scope module mux5in1_tb $end
$var wire 8 ! o_data [7:0] $end
$var parameter 32 " NANOS $end
$var reg 8 # data_a [7:0] $end
$var reg 8 $ data_b [7:0] $end
$var reg 1 % i_clk $end
$var reg 3 & i_cntr [2:0] $end
$var reg 1 ' i_reset $end
$scope module mux5in1 $end
$var wire 8 ( data_a [7:0] $end
$var wire 8 ) data_b [7:0] $end
$var wire 1 % i_clk $end
$var wire 3 * i_cntr [2:0] $end
$var wire 1 ' i_reset $end
$var reg 8 + o_data [7:0] $end
$upscope $end
$upscope $end
$enddefinitions $end
$comment Show the parameter values. $end
$dumpall
b1 "
$end
#0
$dumpvars
bx +
b0 *
b0 )
b0 (
0'
b0 &
0%
b0 $
b0 #
bx !
$end
#3000
b0 !
b0 +
1%
1'
#5000
b1 #
b1 (
#6000
0%
#7000
b1 &
b1 *
#8000
0'
#9000
1%
#10000
b10 #
b10 (
b10 $
b10 )
#12000
0%
#14000
b10 &
b10 *
#15000
1%
b11 #
b11 (
#18000
0%
#20000
b100 #
b100 (
b100 $
b100 )
#21000
1%
b11 &
b11 *
#24000
0%
#25000
b101 #
b101 (
#27000
1%
#28000
b100 &
b100 *
#30000
0%
b110 #
b110 (
b110 $
b110 )
#33000
1%
#35000
b111 #
b111 (
b101 &
b101 *
#36000
0%
#39000
1%
#40000
b1000 #
b1000 (
b1000 $
b1000 )
#42000
0%
b110 &
b110 *
#45000
1%
b1001 #
b1001 (
#48000
0%
#49000
b111 &
b111 *
#50000
b1010 #
b1010 (
b1010 $
b1010 )
#51000
1%
#54000
0%
#55000
b1011 #
b1011 (
#56000
b0 &
b0 *
#57000
b1011 !
b1011 +
1%
#60000
0%
b1100 #
b1100 (
b1100 $
b1100 )
#63000
b1100 !
b1100 +
1%
b1 &
b1 *
#65000
b1101 #
b1101 (
#66000
0%
#69000
1%
#70000
b1110 #
b1110 (
b10 &
b10 *
b1110 $
b1110 )
#72000
0%
#75000
b0 !
b0 +
1%
b1111 #
b1111 (
#77000
b11 &
b11 *
#78000
0%
#80000
b10000 #
b10000 (
b10000 $
b10000 )
#81000
1%
#84000
0%
b100 &
b100 *
#85000
b10001 #
b10001 (
#87000
1%
#90000
0%
b10010 #
b10010 (
b10010 $
b10010 )
#91000
b101 &
b101 *
#93000
1%
#95000
b10011 #
b10011 (
#96000
0%
#98000
b110 &
b110 *
